{"UAc7kepzJPkrSn4uqTRvmw==":"background4.jpg","//RzFZlUu00jU4f1MU+AEQ==":"jasapembuatanwebsitepekanbaru-4-1600x900.jpg","jLHJKHoMal0f6UzaeU1Tjg==":"cooltext374680744223468-432x98.png","LePCmhsX3xUnnClNEGld1A==":"zen2cool.png","tgexZauLjQxFnK2Cbtcmsg==":"mbr.jpg","2nd9wWfnbjyeQxnOB/EkjA==":"mbr-1920x1271.jpg","lUB7CHsssNg8zGj3tJBOag==":"tempat-wisata-pekanbaru-1-1024x768.jpg","Zi0QRXr+oW1yEORBn/2wQA==":"cooltext374680744223468-470x107.png","Lzfpf0z4IpsssmuDwm1XHQ==":"background8.jpg","hDwbqD3styzAjh92HdNSvw==":"wisata-pekanbaru-7-riau-berbagi-copy-900x508.jpg","EpuPQc1ngtAekmVmV8dGzg==":"background4-1.jpg","lYeeYXE2/3UlI4L1xQjiig==":"mbr-1920x1079.jpg","PP85gd1sNHGDQpLIWsoqbw==":"image_-_website_types_.jpeg-900x506.jpg","YUdinVFpMI0KgMp2/IiTyw==":"pic-4-1485771988-1920x1356.jpg","2XkcdKqoYWv3Fu86Epiwjg==":"pic-6-1920x1268.jpg","jgHkVFvyHXhYi2wRIfEY+g==":"bg-01-free-img-1920x1080.jpg","tnKXsPi/mKLNc2oL/SSSPg==":"background1-1.jpg","rrGTGeZ15vDliVOj/tt/LQ==":"background3-1.jpg","fiaTELGKDc22dIKOudSrNA==":"danau-toba-wisata-feature-1200x628.jpg","yj/v6/6EsnFbEvNYsEYbJQ==":"03-2.jpg","6u2JJ/8I0P0QZHNF7cOewg==":"04-3.jpg","+jm/0HQ2iotM+wYTodGCFg==":"05-4.jpg","RN6PgHG0rIegB1pM92ExKA==":"06-5.jpg","h7MxylCgjGaRTqw8wHy8aw==":"02-1.jpg","UpywcY3IcJAIGbOOJYi1Zw==":"08-6.jpg","YMPXnXbkfC0HypAqzXRkWg==":"mbr-1920x1276.jpg","NBsmGossF3zcg9iJeL2TYg==":"hi-tech-tehnologii-internet-1440x900.jpg","Vst244VaJdpjSSEjyEJ0Fg==":"wallpaperflare.com_wallpaper-2000x1250.jpg","z9hbgy5vQTzSJW8fKITcWw==":"rock_steady_technology_3796x2780-2000x1465.jpg","j5VWQPUXRhTpkoHbsFeV2w==":"tempat-wisata-pekanbaru-2-1600x900.jpg","X09TmG8O6A4ZnpeXQjcHtA==":"spa3-1920x1280.jpg","PEVS9F2IAfXMfKxJ1Z2U+A==":"elijah-o-donnell-jjtuqcpqoai-unsplash-1920x1280.jpg","Ee35fUSvglOy5J0iN6gurQ==":"hans-vivek-uimkbvdqsaa-unsplash-1920x1280.jpg","YoaFoAnnW1vbkp6LpHwz6Q==":"jasapembuatanwebsitepekanbaru-6-1600x900.jpg","8ULDQbQnjWVJEe0rQzhtlg==":"jasa_pembuatan_website_di_pekanbaru(11)-1440x900.jpg","5rds1Db4ReyeP/NoLW3d9w==":"jasa_pembuatan_website_di_pekanbaru(3)-85x48.png","GVA13sjt3B0wwZOz+0cmWQ==":"jasa_pembuatan_website_di_pekanbaru(23)-1600x900.jpg","HiXTMaKKl5UZs3AVjpjwNw==":"jasa_pembuatan_website_di_pekanbaru(11)-1080x675.jpg","5wkjfsNQXgGkPTfmhWpnNQ==":"jasa_pembuatan_website_di_pekanbaru(11)-1-1440x900.jpg","SHONzG2V7Isg2ZaKs0uZBg==":"jasa_pembuatan_website_di_pekanbaru(23)-1-1600x900.jpg","1UD4Q/0P2owCwVBXJuxxnw==":"jasa_pembuatan_website_di_pekanbaru(17)-900x508.jpg","w3l6ryexi9fZT7uA1qt/5w==":"jasa_pembuatan_website_di_pekanbaru(18)-1600x900.jpg","Mj9PFLC1evx4cISvOzKFKg==":"jasa-pembuatan-website-di-pekanbaru-11-1-1440x900.jpg","rpAv1lzN+Ir5y51uk/U1Zw==":"jasa-pembuatan-website-di-pekanbaru-23-1-1600x900.jpg","Wp6y0maA6MJWm8YwwlC3rA==":"jasa-pembuatan-website-di-pekanbaru-11-1-1080x675.jpg","a67frumxPFUuqC/RLiBGZw==":"jasa-pembuatan-website-di-pekanbaru-17-900x508.jpg","xMg5UoJ+X1siMYfITKvPmA==":"danau-toba-wisata-feature-1-1200x628.jpg","55OeBKfVxL8SE0WsJ//3pA==":"pic-4-1485771988-1600x900.jpg","IDvUzQR2DOTDWcWg8wATBA==":"jasapembuatanwebsitepekanbaru-3-1600x900.jpg","f3YrTf6v8tF5tpU27/o3pg==":"pic-4-1485771989-1600x900.jpg","s9No4jl74fU8Z2+psz5Onw==":"tempat-wisata-pekanbaru-2-1600x900.jpg","3tRs4Y1TS92A58uWhZTtUQ==":"slide3.jpg","T7PtZPzW1M8fkKPZSVLSrw==":"slide3-1-1600x900.jpg"}